Metadata-Version: 2.1
Name: textract-plus
Version: 0.1b0
Summary: A fork from textract with extended extension support and features. No more muss. No more fuss.
Home-page: https://github.com/VaibhavHaswani/textract-plus
Author: Vaibhav Haswani
Author-email: vaibhavhaswani@gmail.com
License: MIT
Download-URL: https://github.com/VaibhavHaswani/textract-plus/archive/refs/tags/v0.1-beta.tar.gz
Keywords: TEXT EXTRACTION,TEXTRACT,DOCUMENT PARSING
Platform: UNKNOWN
Provides-Extra: pocketsphinx
